{
  "sections": {
    "quiz-section": {
      "type": "quiz-section",
      "blocks": {
        "content_gRLxwr": {
          "type": "content",
          "settings": {
            "heading": "Heading Title",
            "description": "Nous sommes des épicuriens exigeants! des amoureux du goût, des couleurs, des plantes qui font du bien.",
            "cta_text": "Button text",
            "cta_link": "#",
            "image_desktop": "shopify:\/\/shop_images\/2.svg"
          }
        }
      },
      "block_order": [
        "content_gRLxwr"
      ],
      "settings": {
      }
    }
  },
  "order": [
    "quiz-section"
  ]
}